puc_lpgomes_csvconverter/__init__.py
puc_lpgomes_csvconverter/converter.py
puc_lpgomes_csvconverter-0.1.5.dist-info/entry_points.txt
puc_lpgomes_csvconverter-0.1.5.dist-info/WHEEL
puc_lpgomes_csvconverter-0.1.5.dist-info/METADATA
puc_lpgomes_csvconverter-0.1.5.dist-info/RECORD
